README.md
setup.cfg
setup.py
symmetry_py/__init__.py
symmetry_py.egg-info/PKG-INFO
symmetry_py.egg-info/SOURCES.txt
symmetry_py.egg-info/dependency_links.txt
symmetry_py.egg-info/top_level.txt
symmetry_py/database/__init__.py
symmetry_py/database/models/__init__.py
symmetry_py/database/models/_template.py
symmetry_py/database/models/base_model.py
symmetry_py/database/models/process.py
symmetry_py/database/models/process_log.py
symmetry_py/database/models/process_state.py
symmetry_py/util/__init__.py
symmetry_py/util/equinox.py