Metadata-Version: 1.0
Name: symmetry-py
Version: 0.0.21
Summary: Symmetry
Home-page: https://github.com/logistio/symmetry_py
Author: Logistio Software
Author-email: sudo@logistio.ie
License: MIT
Platform: UNKNOWN
